kaniko_wrapper/__init__.py
kaniko_wrapper/kaniko_wrapper.py
kaniko_wrapper/setting.py
kaniko_wrapper/helper/__init__.py
kaniko_wrapper/helper/_dataclass.py
kaniko_wrapper/helper/class_kaniko.py
kaniko_wrapper/helper/helper.py
kaniko_wrapper/helper/log_print.py
kaniko_wrapper-2.0.0.2.post1.dist-info/METADATA
kaniko_wrapper-2.0.0.2.post1.dist-info/WHEEL
kaniko_wrapper-2.0.0.2.post1.dist-info/entry_points.txt
kaniko_wrapper-2.0.0.2.post1.dist-info/licenses/LICENSE
kaniko_wrapper-2.0.0.2.post1.dist-info/RECORD
