Metadata-Version: 2.4
Name: kaniko-wrapper
Version: 2.0.0.2.post1
Summary: EpicMorg: Kaniko-Compose Wrapper - CLI wrapper for Kaniko build system
Project-URL: Homepage, https://github.com/EpicMorg/kaniko-wrapper
Project-URL: Documentation, https://github.com/EpicMorg/kaniko-wrapper/blob/master/README.md
Project-URL: Repository, https://github.com/EpicMorg/kaniko-wrapper.git
Project-URL: Bug Tracker, https://github.com/EpicMorg/kaniko-wrapper/issues
Project-URL: Changelog, https://github.com/EpicMorg/kaniko-wrapper/blob/master/CHANGELOG.md
Author-email: Marry <okomarova@saber.games>, EpicMorg <developer@epicm.org>
Maintainer-email: Marry <okomarova@saber.games>, EpicMorg <developer@epicm.org>
License: MIT License
License-File: LICENSE
Keywords: build,ci,docker,kaniko,wrapper
Classifier: License :: OSI Approved :: MIT License
Classifier: Operating System :: Unix
Classifier: Programming Language :: Python :: 3
Requires-Python: >=3.8
Requires-Dist: click
Requires-Dist: colorlog
Requires-Dist: pydantic-settings
Requires-Dist: pytest
Requires-Dist: python-dotenv
Requires-Dist: pyyaml
Requires-Dist: termcolor
Requires-Dist: toml<0.11.0,>=0.10.2
